pyuv/__init__.py
pyuv/_cpyuv.pyd
pyuv/_version.py
pyuv-1.4.0.dist-info/DESCRIPTION.rst
pyuv-1.4.0.dist-info/METADATA
pyuv-1.4.0.dist-info/RECORD
pyuv-1.4.0.dist-info/WHEEL
pyuv-1.4.0.dist-info/metadata.json
pyuv-1.4.0.dist-info/top_level.txt
